{"retCode":0,"retMsg":"OK","result":{"category":"linear","list":[{"symbol":"ZROUSDT","lastPrice":"2.2659","indexPrice":"2.2717","markPrice":"2.2673","prevPrice24h":"2.2323","price24hPcnt":"0.015051","highPrice24h":"2.3176","lowPrice24h":"2.1816","prevPrice1h":"2.2512","openInterest":"8815534","openInterestValue":"19987460.24","turnover24h":"10905739.8016","volume24h":"4852072.6000","fundingRate":"-0.00010595","nextFundingTime":"1773763200000","predictedDeliveryPrice":"","basisRate":"","deliveryFeeRate":"","deliveryTime":"0","ask1Size":"37.6","bid1Price":"2.2662","ask1Price":"2.2663","bid1Size":"23.7","basis":"","preOpenPrice":"","preQty":"","curPreListingPhase":"","fundingIntervalHour":"4","basisRateYear":"","fundingCap":"0.02"}]},"retExtInfo":[],"time":1773760288963}