{"retCode":0,"retMsg":"OK","result":{"category":"linear","list":[{"symbol":"HYPEUSDT","lastPrice":"40.151","indexPrice":"40.179","markPrice":"40.148","prevPrice24h":"38.818","price24hPcnt":"0.034339","highPrice24h":"41.834","lowPrice24h":"38.636","prevPrice1h":"40.854","openInterest":"6624096.5","openInterestValue":"265944226.28","turnover24h":"249902655.5154","volume24h":"6169791.5200","fundingRate":"0.0001","nextFundingTime":"1773763200000","predictedDeliveryPrice":"","basisRate":"","deliveryFeeRate":"","deliveryTime":"0","ask1Size":"11.53","bid1Price":"40.144","ask1Price":"40.145","bid1Size":"0.14","basis":"","preOpenPrice":"","preQty":"","curPreListingPhase":"Finished","fundingIntervalHour":"8","basisRateYear":"","fundingCap":"0.0063"}]},"retExtInfo":[],"time":1773760407411}