{"retCode":0,"retMsg":"OK","result":{"category":"linear","list":[{"symbol":"BCHUSDT","lastPrice":"473.50","indexPrice":"474.09","markPrice":"473.54","prevPrice24h":"476.10","price24hPcnt":"-0.005461","highPrice24h":"483.70","lowPrice24h":"470.90","prevPrice1h":"473.60","openInterest":"97607.74","openInterestValue":"46221169.20","turnover24h":"19624839.8930","volume24h":"41201.3900","fundingRate":"-0.00013111","nextFundingTime":"1773763200000","predictedDeliveryPrice":"","basisRate":"","deliveryFeeRate":"","deliveryTime":"0","ask1Size":"0.07","bid1Price":"473.50","ask1Price":"473.60","bid1Size":"19.78","basis":"","preOpenPrice":"","preQty":"","curPreListingPhase":"","fundingIntervalHour":"8","basisRateYear":"","fundingCap":"0.01"}]},"retExtInfo":[],"time":1773760333999}